gdirsync/__init__.py
gdirsync/gdirsync.py
Gdirsync-0.1.0.dist-info/LICENSE
Gdirsync-0.1.0.dist-info/METADATA
Gdirsync-0.1.0.dist-info/WHEEL
Gdirsync-0.1.0.dist-info/top_level.txt
Gdirsync-0.1.0.dist-info/RECORD
