Metadata-Version: 2.1
Name: Gdirsync
Version: 0.1.0
Summary: Simple multi-platform file syncing tool
Home-page: https://github.com/chrisbeardy/Gdirsync
Author: Christopher Beard
Author-email: christopherbeard@pm.me
License: UNKNOWN
Keywords: directory,folder,update,synchronisation
Platform: UNKNOWN
Classifier: Programming Language :: Python :: 3
Classifier: Programming Language :: Python :: 3.5
Classifier: Programming Language :: Python :: 3.6
Classifier: Programming Language :: Python :: 3.7
Classifier: License :: OSI Approved :: GNU General Public License v3 or later (GPLv3+)
Classifier: Operating System :: OS Independent
Classifier: Intended Audience :: End Users/Desktop
Classifier: Topic :: Utilities
Classifier: Topic :: Desktop Environment
Classifier: Topic :: System :: Archiving :: Backup
Classifier: Topic :: System :: Archiving :: Mirroring
Requires-Python: >=3.5
